{"dataset": "p_statistics", "title": "Importance: to fulfil one's potential", "label": "Importance: to fulfil one's potential", "label_de": "Wichtigkeit: Sich selbst verwirklichen", "variable": "plh0106", "values": [-8, -7, -6, -5, -4, -3, -2, -1, 1, 2, 3, 4], "value_labels": ["Question not part of the survey program this year", "Only available in less restricted edition", "Version of questionnaire with modified filtering", "Not included in this version of the questionnaire", "Inadmissable multiple response", "Implausible value", "Does not apply", "No answer / don't know", "Very important", "Important", "Less important", "Unimportant"], "start_year": 1984, "end_year": 2021}